ct_viewer/__init__.py
ct_viewer/ct_viewer.py
ct_viewer/.vscode/launch.json
ct_viewer/.vscode/settings.json
ct_viewer/ct_processes/AnalysisView.py
ct_viewer/ct_processes/CTVolume.py
ct_viewer/ct_processes/DICOM_Tags.py
ct_viewer/ct_processes/FileDialog.py
ct_viewer/ct_processes/Globals.py
ct_viewer/ct_processes/ImageTools.py
ct_viewer/ct_processes/InformationBox.py
ct_viewer/ct_processes/Landmarks.py
ct_viewer/ct_processes/MainView.py
ct_viewer/ct_processes/MenuBar.py
ct_viewer/ct_processes/NewMainView.py
ct_viewer/ct_processes/NodeEditor.py
ct_viewer/ct_processes/OptionValue.py
ct_viewer/ct_processes/OptionsPanel.py
ct_viewer/ct_processes/Textures.py
ct_viewer/ct_processes/Themes.py
ct_viewer/ct_processes/VolumeLayer.py
ct_viewer/ct_processes/VolumeOperations.py
ct_viewer/ct_processes/__init__.py
ct_viewer/ct_processes/fast_interp.py
ct_viewer/ct_processes/fast_interp_cupy.py
ctviewer_research-0.3.3.3.dist-info/METADATA
ctviewer_research-0.3.3.3.dist-info/WHEEL
ctviewer_research-0.3.3.3.dist-info/entry_points.txt
ctviewer_research-0.3.3.3.dist-info/top_level.txt
ctviewer_research-0.3.3.3.dist-info/RECORD
