Metadata-Version: 2.4
Name: CTViewer-Research
Version: 0.3.3.3
Summary: A medical imaging viewer for CT scans with advanced analysis features.
Author: Peter Boyle
License: Proprietary
Project-URL: Homepage, https://github.com/pcboyle/CTViewer
Keywords: medical imaging,DICOM,Nifti,cupy,dearpygui
Classifier: Programming Language :: Python :: 3.12
Classifier: Development Status :: 4 - Beta
Classifier: Intended Audience :: Developers
Classifier: Intended Audience :: Science/Research
Classifier: Topic :: Scientific/Engineering :: Medical Science Apps.
Classifier: Topic :: Scientific/Engineering :: Visualization
Requires-Python: >=3.12
Requires-Dist: colorcet
Requires-Dist: h5py
Requires-Dist: cupy
Requires-Dist: numpy
Requires-Dist: pandas
Requires-Dist: numba
Requires-Dist: scipy
Requires-Dist: quaternionic
Requires-Dist: dearpygui>=2.0.0
Requires-Dist: matplotlib
Requires-Dist: openpyxl
Requires-Dist: xlsxwriter
Requires-Dist: nibabel
Requires-Dist: python-gdcm>=3.0.24.1
